firefly_uas/__init__.py
firefly_uas/__main__.py
firefly_uas/base.py
firefly_uas/cli.py
firefly_uas/agents/__init__.py
firefly_uas/agents/drone.py
firefly_uas/gui/__init__.py
firefly_uas/gui/area.py
firefly_uas/location/__init__.py
firefly_uas/location/model.py
firefly_uas/location/utils/__init__.py
firefly_uas/location/utils/math_utils.py
firefly_uas/post/__init__.py
firefly_uas/post/plot.py
firefly_uas/post/utils/__init__.py
firefly_uas/post/utils/plot_utils.py
firefly_uas/prep/__init__.py
firefly_uas/prep/config.py
firefly_uas/prep/distances.py
firefly_uas/prep/grid.py
firefly_uas/prep/osm.py
firefly_uas/prep/setup_runs.py
firefly_uas/prep/utils.py
firefly_uas/run/__init__.py
firefly_uas/run/run.py
firefly_uas-0.1.0.dist-info/LICENSE
firefly_uas-0.1.0.dist-info/METADATA
firefly_uas-0.1.0.dist-info/WHEEL
firefly_uas-0.1.0.dist-info/entry_points.txt
firefly_uas-0.1.0.dist-info/top_level.txt
firefly_uas-0.1.0.dist-info/RECORD
